mmai/VERSION
mmai/__init__.py
mmai/utils.py
mmai_utils-0.1.3.dist-info/METADATA
mmai_utils-0.1.3.dist-info/WHEEL
mmai_utils-0.1.3.dist-info/top_level.txt
mmai_utils-0.1.3.dist-info/RECORD
